tidify/__init__.py
tidify/tidify.py
tidify-0.1.2.dist-info/WHEEL
tidify-0.1.2.dist-info/METADATA
tidify-0.1.2.dist-info/RECORD
