Metadata-Version: 2.1
Name: tidify
Version: 0.1.2
Summary: Convert nested objects into tidy data
Home-page: https://github.com/tangibleintelligence/tidify
License: MIT
Keywords: Tidy Data,Data Analysis
Author: Austin Howard
Author-email: austin@tangibleintelligence.com
Requires-Python: >=3.8,<4.0
Classifier: Development Status :: 4 - Beta
Classifier: License :: OSI Approved :: MIT License
Classifier: Programming Language :: Python :: 3
Classifier: Programming Language :: Python :: 3.10
Classifier: Programming Language :: Python :: 3.8
Classifier: Programming Language :: Python :: 3.9
Requires-Dist: pandas (>=1.4.2,<2.0.0)
Project-URL: Repository, https://github.com/tangibleintelligence/tidify
